pyplaato/__init__.py
pyplaato/const.py
pyplaato/plaato.py
pyplaato/models/__init__.py
pyplaato/models/airlock.py
pyplaato/models/device.py
pyplaato/models/keg.py
pyplaato/models/pins.py
pyplaato-0.0.18.dist-info/LICENSE
pyplaato-0.0.18.dist-info/METADATA
pyplaato-0.0.18.dist-info/WHEEL
pyplaato-0.0.18.dist-info/top_level.txt
pyplaato-0.0.18.dist-info/RECORD
