Metadata-Version: 2.1
Name: pyplaato
Version: 0.0.18
Summary: Asynchronous Python client for getting Plaato Airlock and Keg data
Home-page: https://github.com/JohNan/pyplaato
Author: JohNan
Author-email: johan.nanzen@gmail.com
License: UNKNOWN
Platform: UNKNOWN
Classifier: Framework :: AsyncIO
Classifier: Programming Language :: Python :: 3
Classifier: Programming Language :: Python :: 3.7
Classifier: License :: OSI Approved :: MIT License
Classifier: Operating System :: OS Independent
Classifier: Topic :: Software Development :: Libraries :: Python Modules
Requires-Python: >=3
License-File: LICENSE
